pynadc/__init__.py
pynadc/gosat/__init__.py
pynadc/gosat/db.py
pynadc/gosat2/__init__.py
pynadc/gosat2/db.py
pynadc/gosat2/db_l2.py
pynadc/scia/__init__.py
pynadc/scia/clus_def.py
pynadc/scia/db.py
pynadc/scia/hk.py
pynadc/scia/lv0.py
pynadc/scia/lv1.py
pynadc-1.2.6.data/scripts/add_entry_gosat.py
pynadc-1.2.6.data/scripts/add_entry_gosat2.py
pynadc-1.2.6.data/scripts/add_entry_gosat2_l2.py
pynadc-1.2.6.data/scripts/add_entry_scia.py
pynadc-1.2.6.data/scripts/collect_scia_states.py
pynadc-1.2.6.data/scripts/inquire_gosat.py
pynadc-1.2.6.data/scripts/inquire_gosat2.py
pynadc-1.2.6.data/scripts/inquire_gosat2_l2.py
pynadc-1.2.6.data/scripts/inquire_scia.py
pynadc-1.2.6.data/scripts/scia_lv0.py
pynadc-1.2.6.data/scripts/scia_lv1.py
pynadc-1.2.6.dist-info/METADATA
pynadc-1.2.6.dist-info/WHEEL
pynadc-1.2.6.dist-info/top_level.txt
pynadc-1.2.6.dist-info/RECORD
