Metadata-Version: 2.1
Name: pynadc
Version: 1.2.6
Summary: Python Sciamachy/GOSAT/Tropomi read and SQLite3 library
Home-page: https://github.com/rmvanhees/pynadc.git
Author: Richard van Hees
Author-email: r.m.van.hees@sron.nl
Maintainer: Richard van Hees
Maintainer-email: r.m.van.hees@sron.nl
License: BSD 3-Clause License
Classifier: Development Status :: 4 - Beta
Classifier: Intended Audience :: Developers
Classifier: Intended Audience :: Science/Research
Classifier: License :: OSI Approved :: BSD License
Classifier: Operating System :: MacOS :: MacOS X
Classifier: Operating System :: POSIX :: Linux
Classifier: Programming Language :: Python :: 3 :: Only
Classifier: Programming Language :: Python :: 3.8
Classifier: Programming Language :: Python :: 3.9
Classifier: Programming Language :: Python :: 3.10
Classifier: Topic :: Scientific/Engineering :: Atmospheric Science
Requires-Python: >=3.8
Requires-Dist: bitstring (>=3.1)
Requires-Dist: numpy (>=1.19)
Requires-Dist: h5py (>=3.5)
Provides-Extra: toml
Requires-Dist: toml ; extra == 'toml'
